{"_ts":[1501842074],"_r":{"breakdown":{"html":{"bytes":[49406],"requests":[3]},"js":{"bytes":[211747],"requests":[9]},"css":{"bytes":[14851],"requests":[1]},"image":{"bytes":[425509],"requests":[6]},"flash":{"bytes":[0],"requests":[0]},"font":{"bytes":[72166],"requests":[4]},"other":{"bytes":[1774],"requests":[4]}},"date":[1501842074],"domElements":[443],"domInteractive":[545],"firstPaint":[447],"fullyLoaded":[1934],"id":["170804_VQ_VXG"],"loadTime":[1753],"render":[1205],"SpeedIndex":[1688],"TTFB":[232],"videoFrames":[[{"_i":"frame_0000.jpg","_t":0,"_vc":0},{"_i":"frame_0012.jpg","_t":1200,"_vc":39},{"_i":"frame_0020.jpg","_t":2000,"_vc":100}]],"visualComplete":[2000],"lighthouse":[null],"pagespeed":[85]}}