{"_ts":[1538380037,1538436151],"_r":{"breakdown":{"html":{"bytes":[58518,58518],"requests":[5,5]},"js":{"bytes":[224065,224087],"requests":[7,7]},"css":{"bytes":[7304,7306],"requests":[1,1]},"image":{"bytes":[828466,828407],"requests":[27,27]},"flash":{"bytes":[0,0],"requests":[0,0]},"font":{"bytes":[209110,206112],"requests":[5,5]},"video":{"bytes":[0,0],"requests":[0,0]},"other":{"bytes":[3811,3812],"requests":[3,3]}},"date":[1538380037,1538436151],"domElements":[918,918],"domInteractive":[588,697],"firstPaint":[569.4000000076,577.0000000048],"fullyLoaded":[3114,3097],"id":["181001_Z9_2c4e6ef7316faff4f92f47a272d0052d","181001_RA_4cd9b5028c5edc50b510ad6661620a35"],"loadTime":[2755,2951],"render":[600,600],"SpeedIndex":[808,801],"TTFB":[444,436],"videoFrames":[[{"_i":"ms_000000.jpg","_t":0,"_vc":0},{"_i":"ms_000600.jpg","_t":600,"_vc":55},{"_i":"ms_000800.jpg","_t":800,"_vc":70},{"_i":"ms_000900.jpg","_t":900,"_vc":70},{"_i":"ms_001000.jpg","_t":1000,"_vc":78},{"_i":"ms_001100.jpg","_t":1100,"_vc":89},{"_i":"ms_001200.jpg","_t":1200,"_vc":89},{"_i":"ms_001300.jpg","_t":1300,"_vc":99},{"_i":"ms_001500.jpg","_t":1500,"_vc":98},{"_i":"ms_001600.jpg","_t":1600,"_vc":98},{"_i":"ms_002000.jpg","_t":2000,"_vc":99},{"_i":"ms_002100.jpg","_t":2100,"_vc":99},{"_i":"ms_002200.jpg","_t":2200,"_vc":100}],[{"_i":"ms_000000.jpg","_t":0,"_vc":0},{"_i":"ms_000600.jpg","_t":600,"_vc":55},{"_i":"ms_000700.jpg","_t":700,"_vc":70},{"_i":"ms_000800.jpg","_t":800,"_vc":70},{"_i":"ms_000900.jpg","_t":900,"_vc":78},{"_i":"ms_001000.jpg","_t":1000,"_vc":78},{"_i":"ms_001100.jpg","_t":1100,"_vc":78},{"_i":"ms_001200.jpg","_t":1200,"_vc":89},{"_i":"ms_001400.jpg","_t":1400,"_vc":98},{"_i":"ms_001500.jpg","_t":1500,"_vc":99},{"_i":"ms_001600.jpg","_t":1600,"_vc":99},{"_i":"ms_001700.jpg","_t":1700,"_vc":99},{"_i":"ms_002100.jpg","_t":2100,"_vc":100}]],"visualComplete":[2200,2100],"lighthouse":[57,57],"pagespeed":[80,81]}}